Metadata-Version: 1.1
Name: XStatic-term.js
Version: 0.0.4.1
Summary: term.js 0.0.4 (XStatic packaging standard)
Home-page: https://github.com/chjj/term.js
Author: Thomas Kluyver
Author-email: thomas@kluyver.me.uk
License: (same as term.js)
Keywords: termjs xstatic
Platform: any
Classifier: Environment :: Web Environment
Classifier: License :: OSI Approved :: MIT License
